ynto/ynto.py
ynto-0.0.1.dist-info/LICENSE
ynto-0.0.1.dist-info/METADATA
ynto-0.0.1.dist-info/WHEEL
ynto-0.0.1.dist-info/top_level.txt
ynto-0.0.1.dist-info/RECORD
