Metadata-Version: 2.1
Name: ynto
Version: 0.0.1
Summary: You Never Train Once - yolov8 training system
Author-email: AndrewWetzel23 <andrewwetzel23@gmail.com>
Classifier: Programming Language :: Python :: 3
Classifier: License :: OSI Approved :: MIT License
Classifier: Operating System :: OS Independent
Requires-Python: >3.7
License-File: LICENSE
